string_list/__init__.py
string_list/core.py
string_list-0.1.0.dist-info/licenses/LICENSE
string_list-0.1.0.dist-info/METADATA
string_list-0.1.0.dist-info/WHEEL
string_list-0.1.0.dist-info/top_level.txt
string_list-0.1.0.dist-info/RECORD
