Metadata-Version: 2.4
Name: string-list
Version: 0.1.0
Summary: Tiny but powerful string <-> list manipulation utilities for Python
Author-email: "Kanad Rishiraj (RoamingSaint)" <roamingsaint27@gmail.com>
Requires-Python: >=3.7
License-File: LICENSE
Dynamic: license-file
